Metadata-Version: 1.0
Name: intellimatch
Version: 0.2.0
Summary: Intelligent matching/textsearch/cli interactivity that works for humans
Home-page: https://bitbucket.org/codyc54321/intellimatch
Author: Cody Childers
Author-email: cchilder@mail.usf.edu
License: MIT
Platform: UNKNOWN
